hello_ana_package/__init__.py
hello_ana_package/hello.py
hello_ana_package-0.1.0.dist-info/METADATA
hello_ana_package-0.1.0.dist-info/WHEEL
hello_ana_package-0.1.0.dist-info/top_level.txt
hello_ana_package-0.1.0.dist-info/RECORD
