Metadata-Version: 2.1
Name: hello-ana-package
Version: 0.1.0
Summary: first_package
Author: Ana
Author-email: lumi_mirela@yahoo.com
License: UNKNOWN
Platform: UNKNOWN
